{
    "origin": "ad0ae7b6-f80d-4ba3-be86-2c2c7f86776e",
    "id": "6443",
    "bbox": {
        "min": [
            -3,
            -0.0009708849999999999,
            -3
        ],
        "max": [
            3,
            3.694008,
            3
        ]
    },
    "up": [
        0,
        1,
        0
    ],
    "front": [
        0,
        0,
        1
    ],
    "rooms": [
        {
            "id": "6443_0",
            "modelId": "Bathroom-6473",
            "roomTypes": [
                "Bathroom"
            ],
            "bbox": {
                "min": [
                    -3,
                    0.85,
                    -3
                ],
                "max": [
                    3,
                    1.75,
                    3
                ]
            },
            "origin": "ad0ae7b6-f80d-4ba3-be86-2c2c7f86776e",
            "roomId": 0,
            "objList": [],
            "blockList": [],
            "roomShape": [
                [
                    1.5,
                    -1.5
                ],
                [
                    1.5,
                    1.5
                ],
                [
                    -1.5,
                    1.5
                ],
                [
                    -1.5,
                    -1.5
                ]
            ],
            "roomNorm": [
                [
                    -1,
                    6.123233995736766e-17
                ],
                [
                    -6.123233995736766e-17,
                    -1
                ],
                [
                    1,
                    -6.123233995736766e-17
                ],
                [
                    6.123233995736766e-17,
                    1
                ]
            ],
            "roomOrient": [
                -1.5707963267948966,
                -3.141592653589793,
                1.5707963267948968,
                6.123233995736766e-17
            ],
            "roomShapeBBox": {
                "max": [
                    2.3549915626164686,
                    0.3064598902613379
                ],
                "min": [
                    -3.6751054138264476,
                    -5.6884484112379745
                ]
            }
        }
    ],
    "coarseWallHeight": 2.6,
    "PerspectiveCamera": {
        "fov": 75,
        "focalLength": 35,
        "origin": [
            6.931104242759509e-22,
            5.659676118520787,
            -0.000005659676118522674
        ],
        "rotate": [
            -1.570795326861471,
            3.141592653589793,
            0
        ],
        "target": [
            0,
            0,
            0
        ],
        "roomId": 0,
        "up": [
            -1.2246467991467409e-16,
            0.0000010000000000842668,
            0.9999999999995001
        ]
    },
    "canvas": {
        "width": 2580,
        "height": 1246
    }
}